jetbot_scratch/__init__.py
jetbot_scratch/aruco.py
jetbot_scratch/color.py
jetbot_scratch/digits.py
jetbot_scratch/mnist_trt_b9.pth
jetbot_scratch/object_detect.py
jetbot_scratch/obstacle.py
jetbot_scratch/road.py
jetbot_scratch/ssd_coco_labels.txt
jetbot_scratch/utils.py
jetbot_scratch-0.7.4.dist-info/LICENSE
jetbot_scratch-0.7.4.dist-info/METADATA
jetbot_scratch-0.7.4.dist-info/WHEEL
jetbot_scratch-0.7.4.dist-info/top_level.txt
jetbot_scratch-0.7.4.dist-info/RECORD
