Metadata-Version: 2.1
Name: jetbot-scratch
Version: 0.7.4
Summary: Jetbot 积木编程包
Home-page: https://gitee.com/z14git/jetbot_scratch
Author: z14git
Author-email: lzl1992@gmail.com
Classifier: Programming Language :: Python :: 3
Classifier: License :: OSI Approved :: MIT License
Classifier: Operating System :: OS Independent
Requires-Python: >=3.6
License-File: LICENSE
Requires-Dist: simple-pid
Provides-Extra: all
